agent_instrumentation/__init__.py
agent_instrumentation/_bootstrap/__init__.py
agent_instrumentation/_bootstrap/environment_variables.py
agent_instrumentation/_bootstrap/initialization.py
agent_instrumentation/_bootstrap/sitecustomize.py
agent_instrumentation/cli/__init__.py
agent_instrumentation/cli/main.py
agent_instrumentation-1.0.1.dist-info/METADATA
agent_instrumentation-1.0.1.dist-info/WHEEL
agent_instrumentation-1.0.1.dist-info/entry_points.txt
agent_instrumentation-1.0.1.dist-info/licenses/LICENSE
agent_instrumentation-1.0.1.dist-info/RECORD
