Metadata-Version: 2.4
Name: agent-instrumentation
Version: 1.0.1
Summary: Automatic instrumentation for Python applications using Traceloop SDK
Author-email: Hansi Karunarathna <hansijayanika@gmail.com>
Maintainer-email: Hansi Karunarathna <hansijayanika@gmail.com>
License: Apache-2.0
License-File: LICENSE
Requires-Python: >=3.10
Requires-Dist: traceloop-sdk>=0.47.0
